README.md
setup.py
Flask_HSExcel.egg-info/PKG-INFO
Flask_HSExcel.egg-info/SOURCES.txt
Flask_HSExcel.egg-info/dependency_links.txt
Flask_HSExcel.egg-info/not-zip-safe
Flask_HSExcel.egg-info/requires.txt
Flask_HSExcel.egg-info/top_level.txt
flask_hsexcel/__init__.py
flask_hsexcel/checker.py
flask_hsexcel/models.py
flask_hsexcel/schemy.py
flask_hsexcel/task.py
flask_hsexcel/utils.py
flask_hsexcel/views.py