Metadata-Version: 1.1
Name: Flask-HSExcel
Version: 0.7.0
Summary: 环思的flask导入excel的插件
Home-page: UNKNOWN
Author: Alan Zhang
Author-email: 1095087479@qq.com
License: MIT
Platform: any
Classifier: Framework :: Flask
Classifier: Natural Language :: English
Classifier: Environment :: Web Environment
Classifier: Intended Audience :: Developers
Classifier: License :: OSI Approved :: MIT License
Classifier: Operating System :: OS Independent
Classifier: Programming Language :: Python
Classifier: Topic :: Internet :: WWW/HTTP :: Dynamic Content
Classifier: Topic :: Software Development :: Libraries :: Python Modules
